{
  "node": {
    "6081b25033003c7f92f38e8487db6e7784985856b3": {
      "workers": {
        "app/(dashboard)/[type]/folders/[folderId]/page": {
          "moduleId": "(rsc)/./node_modules/next/dist/build/webpack/loaders/next-flight-action-entry-loader.js?actions=%5B%5B%22%2FUsers%2Fmezri%2FDesktop%2FHehoStory%2Fsrc%2Fapp%2F(dashboard)%2F%5Btype%5D%2Ffolders%2F%5BfolderId%5D%2Fpage.tsx%22%2C%5B%5B%226081b25033003c7f92f38e8487db6e7784985856b3%22%2C%22%24%24RSC_SERVER_ACTION_0%22%5D%5D%5D%5D&__client_imported__=!",
          "async": false
        }
      },
      "layer": {
        "app/(dashboard)/[type]/folders/[folderId]/page": "rsc"
      }
    }
  },
  "edge": {},
  "encryptionKey": "+m5XTU1+hi8f2h6/E572QIb61yXQFQfJgw3pu8oK4B8="
}